recodex_cli/__init__.py
recodex_cli/__main__.py
recodex_cli/console.py
recodex_cli/call_command/command.py
recodex_cli/call_command/command_state.py
recodex_cli/call_command/help_printer.py
recodex_cli/call_command/response_printer.py
recodex_cli/plugins/file_plugins.py
recodex_cli/plugins/info_plugins.py
recodex_cli/utils/client_factory.py
recodex_cli/utils/cmd_utils.py
recodex_cli/utils/login_info.py
recodex_cli-0.2.2.dist-info/licenses/LICENSE
recodex_cli-0.2.2.dist-info/METADATA
recodex_cli-0.2.2.dist-info/WHEEL
recodex_cli-0.2.2.dist-info/entry_points.txt
recodex_cli-0.2.2.dist-info/top_level.txt
recodex_cli-0.2.2.dist-info/RECORD
