Metadata-Version: 2.4
Name: recodex-cli
Version: 0.2.2
Summary: CLI client for ReCodEx API implemented in Python based on recodex-pylib.
Author-email: Vojtech Kloda <vojtech.kloda@gmail.com>, Martin Kruliš <krulis@d3s.mff.cuni.cz>
Project-URL: Homepage, https://github.com/ReCodEx/cli
Project-URL: Issues, https://github.com/ReCodEx/cli/issues
Classifier: Programming Language :: Python :: 3
Classifier: Operating System :: OS Independent
Classifier: License :: OSI Approved :: MIT License
Requires-Python: >=3.11
License-File: LICENSE
Requires-Dist: setuptools>=61.0
Requires-Dist: certifi>=14.05.14
Requires-Dist: typer>=0.16
Requires-Dist: inquirer>=3.4.0
Requires-Dist: recodex-pylib>=0.2.2
Dynamic: license-file
